pysqlgui/__init__.py
pysqlgui/core_database.py
pysqlgui/core_table.py
pysqlgui-1.0.1.dist-info/LICENSE.txt
pysqlgui-1.0.1.dist-info/METADATA
pysqlgui-1.0.1.dist-info/WHEEL
pysqlgui-1.0.1.dist-info/top_level.txt
pysqlgui-1.0.1.dist-info/RECORD
