Metadata-Version: 2.1
Name: pysqlgui
Version: 1.0.1
Summary: A lightweight and intuitive package to interface with SQL in Python.
Home-page: https://github.com/atc2146/pysqlgui
Author: Alex Chung
License: UNKNOWN
Platform: UNKNOWN
Classifier: Programming Language :: Python :: 3
Classifier: License :: OSI Approved :: MIT License
Classifier: Operating System :: OS Independent
Requires-Python: >=3.6
Requires-Dist: pandas
